sudoku/__init__.py
sudoku/sudoku.py
py_sudoku-1.0.3.dist-info/LICENSE
py_sudoku-1.0.3.dist-info/METADATA
py_sudoku-1.0.3.dist-info/WHEEL
py_sudoku-1.0.3.dist-info/top_level.txt
py_sudoku-1.0.3.dist-info/RECORD
