Metadata-Version: 2.1
Name: py-sudoku
Version: 1.0.3
Summary: A Python Sudoku solver
Home-page: https://github.com/jeffsieu/py-sudoku
Author: Jeff Sieu
Author-email: jeffsieu@gmail.com
Keywords: SUDOKU
Classifier: Programming Language :: Python :: 2
Classifier: Programming Language :: Python :: 3
Classifier: License :: OSI Approved :: MIT License
Classifier: Operating System :: OS Independent
Requires-Python: >=2.7
License-File: LICENSE
